pocket_ml/__init__.py
pocket_ml/algorithms/__init__.py
pocket_ml/algorithms/classification/__init__.py
pocket_ml/algorithms/classification/classifier.py
pocket_ml/algorithms/regression/__init__.py
pocket_ml/algorithms/regression/regressor.py
pocket_ml/preprocessing/__init__.py
pocket_ml/preprocessing/data_preprocessor.py
pocket_ml/visualization/__init__.py
pocket_ml/visualization/visualizer.py
pocket_ml-0.1.3.dist-info/METADATA
pocket_ml-0.1.3.dist-info/WHEEL
pocket_ml-0.1.3.dist-info/top_level.txt
pocket_ml-0.1.3.dist-info/RECORD
