Metadata-Version: 2.2
Name: pocket_ml
Version: 0.1.3
Requires-Dist: numpy>=1.19.0
Requires-Dist: pandas>=1.2.0
Requires-Dist: scikit-learn>=0.24.0
Requires-Dist: matplotlib>=3.3.0
Requires-Dist: seaborn>=0.11.0
Requires-Dist: numba>=0.53.0
Dynamic: description
Dynamic: description-content-type
Dynamic: requires-dist
